{
  "url": "https://api.github.com/repos/ethereum/execution-specs/issues/229",
  "repository_url": "https://api.github.com/repos/ethereum/execution-specs",
  "labels_url": "https://api.github.com/repos/ethereum/execution-specs/issues/229/labels{/name}",
  "comments_url": "https://api.github.com/repos/ethereum/execution-specs/issues/229/comments",
  "events_url": "https://api.github.com/repos/ethereum/execution-specs/issues/229/events",
  "html_url": "https://github.com/ethereum/execution-specs/issues/229",
  "id": 938421778,
  "node_id": "MDU6SXNzdWU5Mzg0MjE3Nzg=",
  "number": 229,
  "title": "Add support for t8n tests",
  "user": {
    "login": "lightclient",
    "id": 14004106,
    "node_id": "MDQ6VXNlcjE0MDA0MTA2",
    "avatar_url": "https://avatars.githubusercontent.com/u/14004106?v=4",
    "gravatar_id": "",
    "url": "https://api.github.com/users/lightclient",
    "html_url": "https://github.com/lightclient",
    "followers_url": "https://api.github.com/users/lightclient/followers",
    "following_url": "https://api.github.com/users/lightclient/following{/other_user}",
    "gists_url": "https://api.github.com/users/lightclient/gists{/gist_id}",
    "starred_url": "https://api.github.com/users/lightclient/starred{/owner}{/repo}",
    "subscriptions_url": "https://api.github.com/users/lightclient/subscriptions",
    "organizations_url": "https://api.github.com/users/lightclient/orgs",
    "repos_url": "https://api.github.com/users/lightclient/repos",
    "events_url": "https://api.github.com/users/lightclient/events{/privacy}",
    "received_events_url": "https://api.github.com/users/lightclient/received_events",
    "type": "User",
    "site_admin": false
  },
  "labels": [
    {
      "id": 3146425036,
      "node_id": "MDU6TGFiZWwzMTQ2NDI1MDM2",
      "url": "https://api.github.com/repos/ethereum/execution-specs/labels/A-tool",
      "name": "A-tool",
      "color": "FBCA04",
      "default": false,
      "description": "Area: tooling"
    },
    {
      "id": 3146435194,
      "node_id": "MDU6TGFiZWwzMTQ2NDM1MTk0",
      "url": "https://api.github.com/repos/ethereum/execution-specs/labels/C-enhance",
      "name": "C-enhance",
      "color": "C5DEF5",
      "default": false,
      "description": "Category: a request for an improvement"
    }
  ],
  "state": "open",
  "locked": false,
  "assignee": null,
  "assignees": [

  ],
  "milestone": null,
  "comments": 1,
  "created_at": "2021-07-07T02:40:24Z",
  "updated_at": "2022-03-12T14:30:24Z",
  "closed_at": null,
  "author_association": "MEMBER",
  "active_lock_reason": null,
  "body": "A bit lower priority since we have access to all the `ethereum/tests` now.",
  "closed_by": {
    "login": "SamWilsn",
    "id": 57262657,
    "node_id": "MDQ6VXNlcjU3MjYyNjU3",
    "avatar_url": "https://avatars.githubusercontent.com/u/57262657?v=4",
    "gravatar_id": "",
    "url": "https://api.github.com/users/SamWilsn",
    "html_url": "https://github.com/SamWilsn",
    "followers_url": "https://api.github.com/users/SamWilsn/followers",
    "following_url": "https://api.github.com/users/SamWilsn/following{/other_user}",
    "gists_url": "https://api.github.com/users/SamWilsn/gists{/gist_id}",
    "starred_url": "https://api.github.com/users/SamWilsn/starred{/owner}{/repo}",
    "subscriptions_url": "https://api.github.com/users/SamWilsn/subscriptions",
    "organizations_url": "https://api.github.com/users/SamWilsn/orgs",
    "repos_url": "https://api.github.com/users/SamWilsn/repos",
    "events_url": "https://api.github.com/users/SamWilsn/events{/privacy}",
    "received_events_url": "https://api.github.com/users/SamWilsn/received_events",
    "type": "User",
    "site_admin": false
  },
  "reactions": {
    "url": "https://api.github.com/repos/ethereum/execution-specs/issues/229/reactions",
    "total_count": 0,
    "+1": 0,
    "-1": 0,
    "laugh": 0,
    "hooray": 0,
    "confused": 0,
    "heart": 0,
    "rocket": 0,
    "eyes": 0
  },
  "timeline_url": "https://api.github.com/repos/ethereum/execution-specs/issues/229/timeline",
  "performed_via_github_app": null,
  "state_reason": null
}
[
  {
    "url": "https://api.github.com/repos/ethereum/execution-specs/issues/comments/1065893098",
    "html_url": "https://github.com/ethereum/execution-specs/issues/229#issuecomment-1065893098",
    "issue_url": "https://api.github.com/repos/ethereum/execution-specs/issues/229",
    "id": 1065893098,
    "node_id": "IC_kwDOERgWss4_iDzq",
    "user": {
      "login": "voith",
      "id": 8171193,
      "node_id": "MDQ6VXNlcjgxNzExOTM=",
      "avatar_url": "https://avatars.githubusercontent.com/u/8171193?v=4",
      "gravatar_id": "",
      "url": "https://api.github.com/users/voith",
      "html_url": "https://github.com/voith",
      "followers_url": "https://api.github.com/users/voith/followers",
      "following_url": "https://api.github.com/users/voith/following{/other_user}",
      "gists_url": "https://api.github.com/users/voith/gists{/gist_id}",
      "starred_url": "https://api.github.com/users/voith/starred{/owner}{/repo}",
      "subscriptions_url": "https://api.github.com/users/voith/subscriptions",
      "organizations_url": "https://api.github.com/users/voith/orgs",
      "repos_url": "https://api.github.com/users/voith/repos",
      "events_url": "https://api.github.com/users/voith/events{/privacy}",
      "received_events_url": "https://api.github.com/users/voith/received_events",
      "type": "User",
      "site_admin": false
    },
    "created_at": "2022-03-12T14:30:23Z",
    "updated_at": "2022-03-12T14:30:23Z",
    "author_association": "CONTRIBUTOR",
    "body": "I'm working on this next. ",
    "reactions": {
      "url": "https://api.github.com/repos/ethereum/execution-specs/issues/comments/1065893098/reactions",
      "total_count": 0,
      "+1": 0,
      "-1": 0,
      "laugh": 0,
      "hooray": 0,
      "confused": 0,
      "heart": 0,
      "rocket": 0,
      "eyes": 0
    },
    "performed_via_github_app": null
  }
]
