{
  "url": "https://api.github.com/repos/foundry-rs/foundry/issues/1236",
  "repository_url": "https://api.github.com/repos/foundry-rs/foundry",
  "labels_url": "https://api.github.com/repos/foundry-rs/foundry/issues/1236/labels{/name}",
  "comments_url": "https://api.github.com/repos/foundry-rs/foundry/issues/1236/comments",
  "events_url": "https://api.github.com/repos/foundry-rs/foundry/issues/1236/events",
  "html_url": "https://github.com/foundry-rs/foundry/issues/1236",
  "id": 1197317170,
  "node_id": "I_kwDOGBlvNc5HXZwy",
  "number": 1236,
  "title": "`forge verify-contract` is no longer working due too metadata bytecodeHash is not set to none",
  "user": {
    "login": "pyk",
    "id": 2213646,
    "node_id": "MDQ6VXNlcjIyMTM2NDY=",
    "avatar_url": "https://avatars.githubusercontent.com/u/2213646?v=4",
    "gravatar_id": "",
    "url": "https://api.github.com/users/pyk",
    "html_url": "https://github.com/pyk",
    "followers_url": "https://api.github.com/users/pyk/followers",
    "following_url": "https://api.github.com/users/pyk/following{/other_user}",
    "gists_url": "https://api.github.com/users/pyk/gists{/gist_id}",
    "starred_url": "https://api.github.com/users/pyk/starred{/owner}{/repo}",
    "subscriptions_url": "https://api.github.com/users/pyk/subscriptions",
    "organizations_url": "https://api.github.com/users/pyk/orgs",
    "repos_url": "https://api.github.com/users/pyk/repos",
    "events_url": "https://api.github.com/users/pyk/events{/privacy}",
    "received_events_url": "https://api.github.com/users/pyk/received_events",
    "type": "User",
    "site_admin": false
  },
  "labels": [
    {
      "id": 3334394228,
      "node_id": "MDU6TGFiZWwzMzM0Mzk0MjI4",
      "url": "https://api.github.com/repos/foundry-rs/foundry/labels/T-bug",
      "name": "T-bug",
      "color": "d73a4a",
      "default": false,
      "description": "Type: bug"
    },
    {
      "id": 3703752787,
      "node_id": "LA_kwDOGBlvNc7cwshT",
      "url": "https://api.github.com/repos/foundry-rs/foundry/labels/C-forge",
      "name": "C-forge",
      "color": "5319E7",
      "default": false,
      "description": "Command: forge"
    },
    {
      "id": 3759719259,
      "node_id": "LA_kwDOGBlvNc7gGMNb",
      "url": "https://api.github.com/repos/foundry-rs/foundry/labels/P-high",
      "name": "P-high",
      "color": "D93F0B",
      "default": false,
      "description": "Priority: high"
    },
    {
      "id": 3759720552,
      "node_id": "LA_kwDOGBlvNc7gGMho",
      "url": "https://api.github.com/repos/foundry-rs/foundry/labels/D-easy",
      "name": "D-easy",
      "color": "0E8A16",
      "default": false,
      "description": "Difficulty: easy"
    },
    {
      "id": 3854218343,
      "node_id": "LA_kwDOGBlvNc7lurRn",
      "url": "https://api.github.com/repos/foundry-rs/foundry/labels/Cmd-forge-verify",
      "name": "Cmd-forge-verify",
      "color": "006B75",
      "default": false,
      "description": "Command: forge verify-contract"
    }
  ],
  "state": "closed",
  "locked": false,
  "assignee": null,
  "assignees": [

  ],
  "milestone": null,
  "comments": 6,
  "created_at": "2022-04-08T13:25:39Z",
  "updated_at": "2022-04-12T13:19:45Z",
  "closed_at": "2022-04-12T13:19:44Z",
  "author_association": "CONTRIBUTOR",
  "active_lock_reason": null,
  "body": "### Component\n\nForge\n\n### Have you ensured that all of these are up to date?\n\n- [X] Foundry\n- [X] Foundryup\n\n### What version of Foundry are you on?\n\nforge 0.2.0 (d513291 2022-04-07T18:27:22.910788+00:00)\n\n### What command(s) is the bug in?\n\nforge verify-contract\n\n### Operating System\n\nmacOS (M1)\n\n### Describe the bug\n\nWith recent introduction to use `bytcodeHash` as `None` by default https://github.com/gakonst/foundry/pull/1180, it breaks the `forge verify-contract`.\r\n\r\nEtherscan uses `\"bytecodeHash\": \"ipfs\"` by default to verify the smart contract but foundry doesn't set the metadata bytecode hash to none when submitting contract verification",
  "closed_by": {
    "login": "mattsse",
    "id": 19890894,
    "node_id": "MDQ6VXNlcjE5ODkwODk0",
    "avatar_url": "https://avatars.githubusercontent.com/u/19890894?v=4",
    "gravatar_id": "",
    "url": "https://api.github.com/users/mattsse",
    "html_url": "https://github.com/mattsse",
    "followers_url": "https://api.github.com/users/mattsse/followers",
    "following_url": "https://api.github.com/users/mattsse/following{/other_user}",
    "gists_url": "https://api.github.com/users/mattsse/gists{/gist_id}",
    "starred_url": "https://api.github.com/users/mattsse/starred{/owner}{/repo}",
    "subscriptions_url": "https://api.github.com/users/mattsse/subscriptions",
    "organizations_url": "https://api.github.com/users/mattsse/orgs",
    "repos_url": "https://api.github.com/users/mattsse/repos",
    "events_url": "https://api.github.com/users/mattsse/events{/privacy}",
    "received_events_url": "https://api.github.com/users/mattsse/received_events",
    "type": "User",
    "site_admin": false
  },
  "reactions": {
    "url": "https://api.github.com/repos/foundry-rs/foundry/issues/1236/reactions",
    "total_count": 0,
    "+1": 0,
    "-1": 0,
    "laugh": 0,
    "hooray": 0,
    "confused": 0,
    "heart": 0,
    "rocket": 0,
    "eyes": 0
  },
  "timeline_url": "https://api.github.com/repos/foundry-rs/foundry/issues/1236/timeline",
  "performed_via_github_app": null,
  "state_reason": "completed"
}
[
  {
    "url": "https://api.github.com/repos/foundry-rs/foundry/issues/comments/1092859853",
    "html_url": "https://github.com/foundry-rs/foundry/issues/1236#issuecomment-1092859853",
    "issue_url": "https://api.github.com/repos/foundry-rs/foundry/issues/1236",
    "id": 1092859853,
    "node_id": "IC_kwDOGBlvNc5BI7fN",
    "user": {
      "login": "onbjerg",
      "id": 8862627,
      "node_id": "MDQ6VXNlcjg4NjI2Mjc=",
      "avatar_url": "https://avatars.githubusercontent.com/u/8862627?v=4",
      "gravatar_id": "",
      "url": "https://api.github.com/users/onbjerg",
      "html_url": "https://github.com/onbjerg",
      "followers_url": "https://api.github.com/users/onbjerg/followers",
      "following_url": "https://api.github.com/users/onbjerg/following{/other_user}",
      "gists_url": "https://api.github.com/users/onbjerg/gists{/gist_id}",
      "starred_url": "https://api.github.com/users/onbjerg/starred{/owner}{/repo}",
      "subscriptions_url": "https://api.github.com/users/onbjerg/subscriptions",
      "organizations_url": "https://api.github.com/users/onbjerg/orgs",
      "repos_url": "https://api.github.com/users/onbjerg/repos",
      "events_url": "https://api.github.com/users/onbjerg/events{/privacy}",
      "received_events_url": "https://api.github.com/users/onbjerg/received_events",
      "type": "User",
      "site_admin": false
    },
    "created_at": "2022-04-08T13:27:28Z",
    "updated_at": "2022-04-08T13:27:28Z",
    "author_association": "MEMBER",
    "body": "cc @mattsse why did we disable it in the first place? I forgot",
    "reactions": {
      "url": "https://api.github.com/repos/foundry-rs/foundry/issues/comments/1092859853/reactions",
      "total_count": 0,
      "+1": 0,
      "-1": 0,
      "laugh": 0,
      "hooray": 0,
      "confused": 0,
      "heart": 0,
      "rocket": 0,
      "eyes": 0
    },
    "performed_via_github_app": null
  },
  {
    "url": "https://api.github.com/repos/foundry-rs/foundry/issues/comments/1092875330",
    "html_url": "https://github.com/foundry-rs/foundry/issues/1236#issuecomment-1092875330",
    "issue_url": "https://api.github.com/repos/foundry-rs/foundry/issues/1236",
    "id": 1092875330,
    "node_id": "IC_kwDOGBlvNc5BI_RC",
    "user": {
      "login": "mattsse",
      "id": 19890894,
      "node_id": "MDQ6VXNlcjE5ODkwODk0",
      "avatar_url": "https://avatars.githubusercontent.com/u/19890894?v=4",
      "gravatar_id": "",
      "url": "https://api.github.com/users/mattsse",
      "html_url": "https://github.com/mattsse",
      "followers_url": "https://api.github.com/users/mattsse/followers",
      "following_url": "https://api.github.com/users/mattsse/following{/other_user}",
      "gists_url": "https://api.github.com/users/mattsse/gists{/gist_id}",
      "starred_url": "https://api.github.com/users/mattsse/starred{/owner}{/repo}",
      "subscriptions_url": "https://api.github.com/users/mattsse/subscriptions",
      "organizations_url": "https://api.github.com/users/mattsse/orgs",
      "repos_url": "https://api.github.com/users/mattsse/repos",
      "events_url": "https://api.github.com/users/mattsse/events{/privacy}",
      "received_events_url": "https://api.github.com/users/mattsse/received_events",
      "type": "User",
      "site_admin": false
    },
    "created_at": "2022-04-08T13:43:49Z",
    "updated_at": "2022-04-08T13:43:49Z",
    "author_association": "MEMBER",
    "body": "because that causes non deterministic code, see also https://github.com/Uniswap/v3-core/blob/ed88be38ab2032d82bf10ac6f8d03aa631889d48/hardhat.config.ts#L57-L62\r\n\r\n\r\nbut this is not really a verify issue since that's not included in the verify request we're sending to etherscan, right?\r\n\r\nsounds more like we should consider making ipfs the default?\r\n\r\nand you can adjust this in the foundry.toml",
    "reactions": {
      "url": "https://api.github.com/repos/foundry-rs/foundry/issues/comments/1092875330/reactions",
      "total_count": 0,
      "+1": 0,
      "-1": 0,
      "laugh": 0,
      "hooray": 0,
      "confused": 0,
      "heart": 0,
      "rocket": 0,
      "eyes": 0
    },
    "performed_via_github_app": null
  },
  {
    "url": "https://api.github.com/repos/foundry-rs/foundry/issues/comments/1092881403",
    "html_url": "https://github.com/foundry-rs/foundry/issues/1236#issuecomment-1092881403",
    "issue_url": "https://api.github.com/repos/foundry-rs/foundry/issues/1236",
    "id": 1092881403,
    "node_id": "IC_kwDOGBlvNc5BJAv7",
    "user": {
      "login": "onbjerg",
      "id": 8862627,
      "node_id": "MDQ6VXNlcjg4NjI2Mjc=",
      "avatar_url": "https://avatars.githubusercontent.com/u/8862627?v=4",
      "gravatar_id": "",
      "url": "https://api.github.com/users/onbjerg",
      "html_url": "https://github.com/onbjerg",
      "followers_url": "https://api.github.com/users/onbjerg/followers",
      "following_url": "https://api.github.com/users/onbjerg/following{/other_user}",
      "gists_url": "https://api.github.com/users/onbjerg/gists{/gist_id}",
      "starred_url": "https://api.github.com/users/onbjerg/starred{/owner}{/repo}",
      "subscriptions_url": "https://api.github.com/users/onbjerg/subscriptions",
      "organizations_url": "https://api.github.com/users/onbjerg/orgs",
      "repos_url": "https://api.github.com/users/onbjerg/repos",
      "events_url": "https://api.github.com/users/onbjerg/events{/privacy}",
      "received_events_url": "https://api.github.com/users/onbjerg/received_events",
      "type": "User",
      "site_admin": false
    },
    "created_at": "2022-04-08T13:50:38Z",
    "updated_at": "2022-04-08T13:51:00Z",
    "author_association": "MEMBER",
    "body": "I think it is a verify issue because the metadata hash is added to the end of the bytecode, unsure though",
    "reactions": {
      "url": "https://api.github.com/repos/foundry-rs/foundry/issues/comments/1092881403/reactions",
      "total_count": 0,
      "+1": 0,
      "-1": 0,
      "laugh": 0,
      "hooray": 0,
      "confused": 0,
      "heart": 0,
      "rocket": 0,
      "eyes": 0
    },
    "performed_via_github_app": null
  },
  {
    "url": "https://api.github.com/repos/foundry-rs/foundry/issues/comments/1092888213",
    "html_url": "https://github.com/foundry-rs/foundry/issues/1236#issuecomment-1092888213",
    "issue_url": "https://api.github.com/repos/foundry-rs/foundry/issues/1236",
    "id": 1092888213,
    "node_id": "IC_kwDOGBlvNc5BJCaV",
    "user": {
      "login": "mattsse",
      "id": 19890894,
      "node_id": "MDQ6VXNlcjE5ODkwODk0",
      "avatar_url": "https://avatars.githubusercontent.com/u/19890894?v=4",
      "gravatar_id": "",
      "url": "https://api.github.com/users/mattsse",
      "html_url": "https://github.com/mattsse",
      "followers_url": "https://api.github.com/users/mattsse/followers",
      "following_url": "https://api.github.com/users/mattsse/following{/other_user}",
      "gists_url": "https://api.github.com/users/mattsse/gists{/gist_id}",
      "starred_url": "https://api.github.com/users/mattsse/starred{/owner}{/repo}",
      "subscriptions_url": "https://api.github.com/users/mattsse/subscriptions",
      "organizations_url": "https://api.github.com/users/mattsse/orgs",
      "repos_url": "https://api.github.com/users/mattsse/repos",
      "events_url": "https://api.github.com/users/mattsse/events{/privacy}",
      "received_events_url": "https://api.github.com/users/mattsse/received_events",
      "type": "User",
      "site_admin": false
    },
    "created_at": "2022-04-08T13:57:26Z",
    "updated_at": "2022-04-08T13:57:26Z",
    "author_association": "MEMBER",
    "body": "but the bytecode is not part of the verify payload\r\n \r\nhttps://docs.etherscan.io/api-endpoints/contracts#source-code-submission-gist",
    "reactions": {
      "url": "https://api.github.com/repos/foundry-rs/foundry/issues/comments/1092888213/reactions",
      "total_count": 1,
      "+1": 1,
      "-1": 0,
      "laugh": 0,
      "hooray": 0,
      "confused": 0,
      "heart": 0,
      "rocket": 0,
      "eyes": 0
    },
    "performed_via_github_app": null
  },
  {
    "url": "https://api.github.com/repos/foundry-rs/foundry/issues/comments/1093314920",
    "html_url": "https://github.com/foundry-rs/foundry/issues/1236#issuecomment-1093314920",
    "issue_url": "https://api.github.com/repos/foundry-rs/foundry/issues/1236",
    "id": 1093314920,
    "node_id": "IC_kwDOGBlvNc5BKqlo",
    "user": {
      "login": "pyk",
      "id": 2213646,
      "node_id": "MDQ6VXNlcjIyMTM2NDY=",
      "avatar_url": "https://avatars.githubusercontent.com/u/2213646?v=4",
      "gravatar_id": "",
      "url": "https://api.github.com/users/pyk",
      "html_url": "https://github.com/pyk",
      "followers_url": "https://api.github.com/users/pyk/followers",
      "following_url": "https://api.github.com/users/pyk/following{/other_user}",
      "gists_url": "https://api.github.com/users/pyk/gists{/gist_id}",
      "starred_url": "https://api.github.com/users/pyk/starred{/owner}{/repo}",
      "subscriptions_url": "https://api.github.com/users/pyk/subscriptions",
      "organizations_url": "https://api.github.com/users/pyk/orgs",
      "repos_url": "https://api.github.com/users/pyk/repos",
      "events_url": "https://api.github.com/users/pyk/events{/privacy}",
      "received_events_url": "https://api.github.com/users/pyk/received_events",
      "type": "User",
      "site_admin": false
    },
    "created_at": "2022-04-08T20:13:19Z",
    "updated_at": "2022-04-08T20:13:19Z",
    "author_association": "CONTRIBUTOR",
    "body": "> I think it is a verify issue because the metadata hash is added to the end of the bytecode, unsure though\r\n\r\n@onbjerg @mattsse Yes the metadata hash is appended to the bytecode, hence the contract verification is failed when `forge` submit the verification using flattened file format instead of standard-input-json. \r\n\r\nWe can only override the metadata setting when using the `standard-input-json` format.\r\n\r\nI have submitted PR on ethers and foundry to solve this problem https://github.com/gakonst/ethers-rs/pull/1126 https://github.com/gakonst/foundry/pull/1242\r\n\r\n",
    "reactions": {
      "url": "https://api.github.com/repos/foundry-rs/foundry/issues/comments/1093314920/reactions",
      "total_count": 0,
      "+1": 0,
      "-1": 0,
      "laugh": 0,
      "hooray": 0,
      "confused": 0,
      "heart": 0,
      "rocket": 0,
      "eyes": 0
    },
    "performed_via_github_app": null
  },
  {
    "url": "https://api.github.com/repos/foundry-rs/foundry/issues/comments/1096719148",
    "html_url": "https://github.com/foundry-rs/foundry/issues/1236#issuecomment-1096719148",
    "issue_url": "https://api.github.com/repos/foundry-rs/foundry/issues/1236",
    "id": 1096719148,
    "node_id": "IC_kwDOGBlvNc5BXpss",
    "user": {
      "login": "mattsse",
      "id": 19890894,
      "node_id": "MDQ6VXNlcjE5ODkwODk0",
      "avatar_url": "https://avatars.githubusercontent.com/u/19890894?v=4",
      "gravatar_id": "",
      "url": "https://api.github.com/users/mattsse",
      "html_url": "https://github.com/mattsse",
      "followers_url": "https://api.github.com/users/mattsse/followers",
      "following_url": "https://api.github.com/users/mattsse/following{/other_user}",
      "gists_url": "https://api.github.com/users/mattsse/gists{/gist_id}",
      "starred_url": "https://api.github.com/users/mattsse/starred{/owner}{/repo}",
      "subscriptions_url": "https://api.github.com/users/mattsse/subscriptions",
      "organizations_url": "https://api.github.com/users/mattsse/orgs",
      "repos_url": "https://api.github.com/users/mattsse/repos",
      "events_url": "https://api.github.com/users/mattsse/events{/privacy}",
      "received_events_url": "https://api.github.com/users/mattsse/received_events",
      "type": "User",
      "site_admin": false
    },
    "created_at": "2022-04-12T13:19:44Z",
    "updated_at": "2022-04-12T13:19:44Z",
    "author_association": "MEMBER",
    "body": "closing as this in no longer the default and we have json verify",
    "reactions": {
      "url": "https://api.github.com/repos/foundry-rs/foundry/issues/comments/1096719148/reactions",
      "total_count": 0,
      "+1": 0,
      "-1": 0,
      "laugh": 0,
      "hooray": 0,
      "confused": 0,
      "heart": 0,
      "rocket": 0,
      "eyes": 0
    },
    "performed_via_github_app": null
  }
]
