{
  "url": "https://api.github.com/repos/ethereum/remix-project/issues/3595",
  "repository_url": "https://api.github.com/repos/ethereum/remix-project",
  "labels_url": "https://api.github.com/repos/ethereum/remix-project/issues/3595/labels{/name}",
  "comments_url": "https://api.github.com/repos/ethereum/remix-project/issues/3595/comments",
  "events_url": "https://api.github.com/repos/ethereum/remix-project/issues/3595/events",
  "html_url": "https://github.com/ethereum/remix-project/issues/3595",
  "id": 1653461420,
  "node_id": "I_kwDODtLRw85ijdGs",
  "number": 3595,
  "title": "Error! Unable to generate Contract ByteCode and ABI (General Exception, unable to get compiled [bytecode])",
  "user": {
    "login": "hassadem",
    "id": 35954739,
    "node_id": "MDQ6VXNlcjM1OTU0NzM5",
    "avatar_url": "https://avatars.githubusercontent.com/u/35954739?v=4",
    "gravatar_id": "",
    "url": "https://api.github.com/users/hassadem",
    "html_url": "https://github.com/hassadem",
    "followers_url": "https://api.github.com/users/hassadem/followers",
    "following_url": "https://api.github.com/users/hassadem/following{/other_user}",
    "gists_url": "https://api.github.com/users/hassadem/gists{/gist_id}",
    "starred_url": "https://api.github.com/users/hassadem/starred{/owner}{/repo}",
    "subscriptions_url": "https://api.github.com/users/hassadem/subscriptions",
    "organizations_url": "https://api.github.com/users/hassadem/orgs",
    "repos_url": "https://api.github.com/users/hassadem/repos",
    "events_url": "https://api.github.com/users/hassadem/events{/privacy}",
    "received_events_url": "https://api.github.com/users/hassadem/received_events",
    "type": "User",
    "site_admin": false
  },
  "labels": [

  ],
  "state": "open",
  "locked": false,
  "assignee": null,
  "assignees": [

  ],
  "milestone": null,
  "comments": 2,
  "created_at": "2023-04-04T08:51:47Z",
  "updated_at": "2023-07-28T11:13:11Z",
  "closed_at": null,
  "author_association": "NONE",
  "active_lock_reason": null,
  "body": "Good Day,\r\n\r\nafter declaring license comment //SPDX follow by the solidity compiler version and import statement from openzeppelin github repository declare your constructor and its arguement. \r\n\r\nThen deployed your contract it deployed, but on getting to etherscan or bscscan and try to verify the contract via  bscscan or etherscan it is not going through saying \"Error! Unable to generate Contract ByteCode and ABI (General Exception, unable to get compiled [bytecode])\" \r\n\r\nThis sound weird as those scans cannot verified contract with import statement deployed on remix, \r\n\r\nunles you deployed on truffle and verified there.\r\n![Screenshot from 2023-04-04 09-44-25](https://user-images.githubusercontent.com/35954739/229739624-86e55562-cb77-4abe-b6ee-abe1a2177f88.png)\r\nthe screenshot is attached for more understanding\r\n![Screenshot from 2023-04-04 09-51-28](https://user-images.githubusercontent.com/35954739/229739949-ac68c811-7047-4e65-923f-bd11101abf95.png)\r\n",
  "closed_by": null,
  "reactions": {
    "url": "https://api.github.com/repos/ethereum/remix-project/issues/3595/reactions",
    "total_count": 0,
    "+1": 0,
    "-1": 0,
    "laugh": 0,
    "hooray": 0,
    "confused": 0,
    "heart": 0,
    "rocket": 0,
    "eyes": 0
  },
  "timeline_url": "https://api.github.com/repos/ethereum/remix-project/issues/3595/timeline",
  "performed_via_github_app": null,
  "state_reason": null
}
[
  {
    "url": "https://api.github.com/repos/ethereum/remix-project/issues/comments/1579277927",
    "html_url": "https://github.com/ethereum/remix-project/issues/3595#issuecomment-1579277927",
    "issue_url": "https://api.github.com/repos/ethereum/remix-project/issues/3595",
    "id": 1579277927,
    "node_id": "IC_kwDODtLRw85eId5n",
    "user": {
      "login": "cryptoqueen23",
      "id": 123911714,
      "node_id": "U_kgDOB2K-Ig",
      "avatar_url": "https://avatars.githubusercontent.com/u/123911714?v=4",
      "gravatar_id": "",
      "url": "https://api.github.com/users/cryptoqueen23",
      "html_url": "https://github.com/cryptoqueen23",
      "followers_url": "https://api.github.com/users/cryptoqueen23/followers",
      "following_url": "https://api.github.com/users/cryptoqueen23/following{/other_user}",
      "gists_url": "https://api.github.com/users/cryptoqueen23/gists{/gist_id}",
      "starred_url": "https://api.github.com/users/cryptoqueen23/starred{/owner}{/repo}",
      "subscriptions_url": "https://api.github.com/users/cryptoqueen23/subscriptions",
      "organizations_url": "https://api.github.com/users/cryptoqueen23/orgs",
      "repos_url": "https://api.github.com/users/cryptoqueen23/repos",
      "events_url": "https://api.github.com/users/cryptoqueen23/events{/privacy}",
      "received_events_url": "https://api.github.com/users/cryptoqueen23/received_events",
      "type": "User",
      "site_admin": false
    },
    "created_at": "2023-06-06T18:44:26Z",
    "updated_at": "2023-06-06T18:44:26Z",
    "author_association": "NONE",
    "body": "I am having the same issue in eth and bsc scan.",
    "reactions": {
      "url": "https://api.github.com/repos/ethereum/remix-project/issues/comments/1579277927/reactions",
      "total_count": 0,
      "+1": 0,
      "-1": 0,
      "laugh": 0,
      "hooray": 0,
      "confused": 0,
      "heart": 0,
      "rocket": 0,
      "eyes": 0
    },
    "performed_via_github_app": null
  },
  {
    "url": "https://api.github.com/repos/ethereum/remix-project/issues/comments/1655509984",
    "html_url": "https://github.com/ethereum/remix-project/issues/3595#issuecomment-1655509984",
    "issue_url": "https://api.github.com/repos/ethereum/remix-project/issues/3595",
    "id": 1655509984,
    "node_id": "IC_kwDODtLRw85irRPg",
    "user": {
      "login": "melihgunduz",
      "id": 72277536,
      "node_id": "MDQ6VXNlcjcyMjc3NTM2",
      "avatar_url": "https://avatars.githubusercontent.com/u/72277536?v=4",
      "gravatar_id": "",
      "url": "https://api.github.com/users/melihgunduz",
      "html_url": "https://github.com/melihgunduz",
      "followers_url": "https://api.github.com/users/melihgunduz/followers",
      "following_url": "https://api.github.com/users/melihgunduz/following{/other_user}",
      "gists_url": "https://api.github.com/users/melihgunduz/gists{/gist_id}",
      "starred_url": "https://api.github.com/users/melihgunduz/starred{/owner}{/repo}",
      "subscriptions_url": "https://api.github.com/users/melihgunduz/subscriptions",
      "organizations_url": "https://api.github.com/users/melihgunduz/orgs",
      "repos_url": "https://api.github.com/users/melihgunduz/repos",
      "events_url": "https://api.github.com/users/melihgunduz/events{/privacy}",
      "received_events_url": "https://api.github.com/users/melihgunduz/received_events",
      "type": "User",
      "site_admin": false
    },
    "created_at": "2023-07-28T11:13:10Z",
    "updated_at": "2023-07-28T11:13:10Z",
    "author_association": "NONE",
    "body": "I fixed \"Error! Unable to generate Contract ByteCode and ABI\" problem with choose optimization selection \"yes\" in bscscan verify screen and verified. ",
    "reactions": {
      "url": "https://api.github.com/repos/ethereum/remix-project/issues/comments/1655509984/reactions",
      "total_count": 0,
      "+1": 0,
      "-1": 0,
      "laugh": 0,
      "hooray": 0,
      "confused": 0,
      "heart": 0,
      "rocket": 0,
      "eyes": 0
    },
    "performed_via_github_app": null
  }
]
